{"nodes":[{"pos":[1184,1198],"content":"ICompositeView","needQuote":true,"needEscape":true,"nodes":[{"content":"ICompositeView","pos":[0,14]}]},{"pos":[1694,1721],"content":"CanPasteItems(List<ph id=\"ph1\">&lt;Object&gt;</ph>)","needQuote":true,"needEscape":true,"source":"CanPasteItems(List<Object>)"},{"pos":[2197,2231],"content":"Parameter description to be filled","needQuote":true,"needEscape":true,"nodes":[{"content":"Parameter description to be filled","pos":[0,34]}]},{"pos":[2290,2324],"content":"Parameter description to be filled","needQuote":true,"needEscape":true,"nodes":[{"content":"Parameter description to be filled","pos":[0,34]}]},{"pos":[2575,2603],"content":"DroppingTypeResolvingOptions","needQuote":true,"needEscape":true,"nodes":[{"content":"DroppingTypeResolvingOptions","pos":[0,28]}]},{"pos":[3086,3120],"content":"Parameter description to be filled","needQuote":true,"needEscape":true,"nodes":[{"content":"Parameter description to be filled","pos":[0,34]}]},{"pos":[3351,3369],"content":"IsDefaultContainer","needQuote":true,"needEscape":true,"nodes":[{"content":"IsDefaultContainer","pos":[0,18]}]},{"pos":[3728,3762],"content":"Parameter description to be filled","needQuote":true,"needEscape":true,"nodes":[{"content":"Parameter description to be filled","pos":[0,34]}]},{"pos":[4075,4097],"content":"OnItemMoved(ModelItem)","needQuote":true,"needEscape":true,"nodes":[{"content":"OnItemMoved(ModelItem)","pos":[0,22]}]},{"pos":[4562,4596],"content":"Parameter description to be filled","needQuote":true,"needEscape":true,"nodes":[{"content":"Parameter description to be filled","pos":[0,34]}]},{"pos":[4979,5009],"content":"OnItemsCopied(List<ph id=\"ph1\">&lt;ModelItem&gt;</ph>)","needQuote":true,"needEscape":true,"source":"OnItemsCopied(List<ModelItem>)"},{"pos":[5564,5598],"content":"Parameter description to be filled","needQuote":true,"needEscape":true,"nodes":[{"content":"Parameter description to be filled","pos":[0,34]}]},{"pos":[5656,5690],"content":"Parameter description to be filled","needQuote":true,"needEscape":true,"nodes":[{"content":"Parameter description to be filled","pos":[0,34]}]},{"pos":[6067,6094],"content":"OnItemsCut(List<ph id=\"ph1\">&lt;ModelItem&gt;</ph>)","needQuote":true,"needEscape":true,"source":"OnItemsCut(List<ModelItem>)"},{"pos":[6638,6672],"content":"Parameter description to be filled","needQuote":true,"needEscape":true,"nodes":[{"content":"Parameter description to be filled","pos":[0,34]}]},{"pos":[6730,6764],"content":"Parameter description to be filled","needQuote":true,"needEscape":true,"nodes":[{"content":"Parameter description to be filled","pos":[0,34]}]},{"pos":[7147,7177],"content":"OnItemsDelete(List<ph id=\"ph1\">&lt;ModelItem&gt;</ph>)","needQuote":true,"needEscape":true,"source":"OnItemsDelete(List<ModelItem>)"},{"pos":[7734,7768],"content":"Parameter description to be filled","needQuote":true,"needEscape":true,"nodes":[{"content":"Parameter description to be filled","pos":[0,34]}]},{"pos":[8323,8389],"content":"OnItemsPasted(List<ph id=\"ph1\">&lt;Object&gt;</ph>,List<ph id=\"ph2\">&lt;Object&gt;</ph>,Point,WorkflowViewElement)","needQuote":true,"needEscape":true,"source":"OnItemsPasted(List<Object>,List<Object>,Point,WorkflowViewElement)"},{"pos":[9098,9132],"content":"Parameter description to be filled","needQuote":true,"needEscape":true,"nodes":[{"content":"Parameter description to be filled","pos":[0,34]}]},{"pos":[9230,9264],"content":"Parameter description to be filled","needQuote":true,"needEscape":true,"nodes":[{"content":"Parameter description to be filled","pos":[0,34]}]},{"pos":[9338,9372],"content":"Parameter description to be filled","needQuote":true,"needEscape":true,"nodes":[{"content":"Parameter description to be filled","pos":[0,34]}]},{"pos":[9485,9519],"content":"Parameter description to be filled","needQuote":true,"needEscape":true,"nodes":[{"content":"Parameter description to be filled","pos":[0,34]}]},{"pos":[9780,9807],"content":"CanPasteItems(List<ph id=\"ph1\">&lt;Object&gt;</ph>)","needQuote":true,"needEscape":true,"source":"CanPasteItems(List<Object>)"},{"pos":[10020,10027],"content":"Boolean","needQuote":true,"needEscape":true,"nodes":[{"content":"Boolean","pos":[0,7]}]},{"pos":[10198,10210],"content":"List<ph id=\"ph1\">&lt;Object&gt;</ph>","needQuote":true,"needEscape":true,"source":"List<Object>"},{"pos":[10465,10493],"content":"DroppingTypeResolvingOptions","needQuote":true,"needEscape":true,"nodes":[{"content":"DroppingTypeResolvingOptions","pos":[0,28]}]},{"pos":[10779,10799],"content":"TypeResolvingOptions","needQuote":true,"needEscape":true,"nodes":[{"content":"TypeResolvingOptions","pos":[0,20]}]},{"pos":[11062,11080],"content":"IsDefaultContainer","needQuote":true,"needEscape":true,"nodes":[{"content":"IsDefaultContainer","pos":[0,18]}]},{"pos":[11275,11282],"content":"Boolean","needQuote":true,"needEscape":true,"nodes":[{"content":"Boolean","pos":[0,7]}]},{"pos":[11531,11553],"content":"OnItemMoved(ModelItem)","needQuote":true,"needEscape":true,"nodes":[{"content":"OnItemMoved(ModelItem)","pos":[0,22]}]},{"pos":[11818,11827],"content":"ModelItem","needQuote":true,"needEscape":true,"nodes":[{"content":"ModelItem","pos":[0,9]}]},{"pos":[12145,12175],"content":"OnItemsCopied(List<ph id=\"ph1\">&lt;ModelItem&gt;</ph>)","needQuote":true,"needEscape":true,"source":"OnItemsCopied(List<ModelItem>)"},{"pos":[12393,12399],"content":"Object","needQuote":true,"needEscape":true,"nodes":[{"content":"Object","pos":[0,6]}]},{"pos":[12601,12616],"content":"List<ph id=\"ph1\">&lt;ModelItem&gt;</ph>","needQuote":true,"needEscape":true,"source":"List<ModelItem>"},{"pos":[12970,12997],"content":"OnItemsCut(List<ph id=\"ph1\">&lt;ModelItem&gt;</ph>)","needQuote":true,"needEscape":true,"source":"OnItemsCut(List<ModelItem>)"},{"pos":[13209,13215],"content":"Object","needQuote":true,"needEscape":true,"nodes":[{"content":"Object","pos":[0,6]}]},{"pos":[13417,13432],"content":"List<ph id=\"ph1\">&lt;ModelItem&gt;</ph>","needQuote":true,"needEscape":true,"source":"List<ModelItem>"},{"pos":[13789,13819],"content":"OnItemsDelete(List<ph id=\"ph1\">&lt;ModelItem&gt;</ph>)","needQuote":true,"needEscape":true,"source":"OnItemsDelete(List<ModelItem>)"},{"pos":[14123,14138],"content":"List<ph id=\"ph1\">&lt;ModelItem&gt;</ph>","needQuote":true,"needEscape":true,"source":"List<ModelItem>"},{"pos":[14581,14647],"content":"OnItemsPasted(List<ph id=\"ph1\">&lt;Object&gt;</ph>,List<ph id=\"ph2\">&lt;Object&gt;</ph>,Point,WorkflowViewElement)","needQuote":true,"needEscape":true,"source":"OnItemsPasted(List<Object>,List<Object>,Point,WorkflowViewElement)"},{"pos":[14990,15002],"content":"List<ph id=\"ph1\">&lt;Object&gt;</ph>","needQuote":true,"needEscape":true,"source":"List<Object>"},{"pos":[15210,15222],"content":"List<ph id=\"ph1\">&lt;Object&gt;</ph>","needQuote":true,"needEscape":true,"source":"List<Object>"},{"pos":[15391,15396],"content":"Point","needQuote":true,"needEscape":true,"nodes":[{"content":"Point","pos":[0,5]}]},{"pos":[15579,15598],"content":"WorkflowViewElement","needQuote":true,"needEscape":true,"nodes":[{"content":"WorkflowViewElement","pos":[0,19]}]}],"content":"### YamlMime:ManagedReference\nitems:\n- uid: System.Activities.Presentation.ICompositeView\n  id: ICompositeView\n  children:\n  - System.Activities.Presentation.ICompositeView.CanPasteItems(System.Collections.Generic.List{System.Object})\n  - System.Activities.Presentation.ICompositeView.DroppingTypeResolvingOptions\n  - System.Activities.Presentation.ICompositeView.IsDefaultContainer\n  - System.Activities.Presentation.ICompositeView.OnItemMoved(System.Activities.Presentation.Model.ModelItem)\n  - System.Activities.Presentation.ICompositeView.OnItemsCopied(System.Collections.Generic.List{System.Activities.Presentation.Model.ModelItem})\n  - System.Activities.Presentation.ICompositeView.OnItemsCut(System.Collections.Generic.List{System.Activities.Presentation.Model.ModelItem})\n  - System.Activities.Presentation.ICompositeView.OnItemsDelete(System.Collections.Generic.List{System.Activities.Presentation.Model.ModelItem})\n  - System.Activities.Presentation.ICompositeView.OnItemsPasted(System.Collections.Generic.List{System.Object},System.Collections.Generic.List{System.Object},System.Windows.Point,System.Activities.Presentation.WorkflowViewElement)\n  langs:\n  - csharp\n  name: ICompositeView\n  nameWithType: ICompositeView\n  fullName: System.Activities.Presentation.ICompositeView\n  type: Interface\n  syntax:\n    content: public interface ICompositeView\n  implements: []\n  platform:\n  - net-11\n  - net-20\n  - netcore-10\n- uid: System.Activities.Presentation.ICompositeView.CanPasteItems(System.Collections.Generic.List{System.Object})\n  id: CanPasteItems(System.Collections.Generic.List{System.Object})\n  parent: System.Activities.Presentation.ICompositeView\n  langs:\n  - csharp\n  name: CanPasteItems(List<Object>)\n  nameWithType: ICompositeView.CanPasteItems(List<Object>)\n  fullName: System.Activities.Presentation.ICompositeView.CanPasteItems(List<Object>)\n  type: Method\n  assemblies:\n  - System.Activities.Presentation\n  namespace: System.Activities.Presentation\n  syntax:\n    content: public bool CanPasteItems (System.Collections.Generic.List<object> itemsToPaste);\n    parameters:\n    - id: itemsToPaste\n      type: System.Collections.Generic.List{System.Object}\n      description: Parameter description to be filled\n    return:\n      type: System.Boolean\n      description: Parameter description to be filled\n  platform:\n  - net-11\n  - net-20\n  - netcore-10\n- uid: System.Activities.Presentation.ICompositeView.DroppingTypeResolvingOptions\n  id: DroppingTypeResolvingOptions\n  parent: System.Activities.Presentation.ICompositeView\n  langs:\n  - csharp\n  name: DroppingTypeResolvingOptions\n  nameWithType: ICompositeView.DroppingTypeResolvingOptions\n  fullName: System.Activities.Presentation.ICompositeView.DroppingTypeResolvingOptions\n  type: Property\n  assemblies:\n  - System.Activities.Presentation\n  namespace: System.Activities.Presentation\n  syntax:\n    content: public System.Activities.Presentation.View.TypeResolvingOptions DroppingTypeResolvingOptions { get; }\n    return:\n      type: System.Activities.Presentation.View.TypeResolvingOptions\n      description: Parameter description to be filled\n  platform:\n  - net-11\n  - net-20\n  - netcore-10\n- uid: System.Activities.Presentation.ICompositeView.IsDefaultContainer\n  id: IsDefaultContainer\n  parent: System.Activities.Presentation.ICompositeView\n  langs:\n  - csharp\n  name: IsDefaultContainer\n  nameWithType: ICompositeView.IsDefaultContainer\n  fullName: System.Activities.Presentation.ICompositeView.IsDefaultContainer\n  type: Property\n  assemblies:\n  - System.Activities.Presentation\n  namespace: System.Activities.Presentation\n  syntax:\n    content: public bool IsDefaultContainer { get; }\n    return:\n      type: System.Boolean\n      description: Parameter description to be filled\n  platform:\n  - net-11\n  - net-20\n  - netcore-10\n- uid: System.Activities.Presentation.ICompositeView.OnItemMoved(System.Activities.Presentation.Model.ModelItem)\n  id: OnItemMoved(System.Activities.Presentation.Model.ModelItem)\n  parent: System.Activities.Presentation.ICompositeView\n  langs:\n  - csharp\n  name: OnItemMoved(ModelItem)\n  nameWithType: ICompositeView.OnItemMoved(ModelItem)\n  fullName: System.Activities.Presentation.ICompositeView.OnItemMoved(ModelItem)\n  type: Method\n  assemblies:\n  - System.Activities.Presentation\n  namespace: System.Activities.Presentation\n  syntax:\n    content: public void OnItemMoved (System.Activities.Presentation.Model.ModelItem modelItem);\n    parameters:\n    - id: modelItem\n      type: System.Activities.Presentation.Model.ModelItem\n      description: Parameter description to be filled\n  platform:\n  - net-11\n  - net-20\n  - netcore-10\n- uid: System.Activities.Presentation.ICompositeView.OnItemsCopied(System.Collections.Generic.List{System.Activities.Presentation.Model.ModelItem})\n  id: OnItemsCopied(System.Collections.Generic.List{System.Activities.Presentation.Model.ModelItem})\n  parent: System.Activities.Presentation.ICompositeView\n  langs:\n  - csharp\n  name: OnItemsCopied(List<ModelItem>)\n  nameWithType: ICompositeView.OnItemsCopied(List<ModelItem>)\n  fullName: System.Activities.Presentation.ICompositeView.OnItemsCopied(List<ModelItem>)\n  type: Method\n  assemblies:\n  - System.Activities.Presentation\n  namespace: System.Activities.Presentation\n  syntax:\n    content: public object OnItemsCopied (System.Collections.Generic.List<System.Activities.Presentation.Model.ModelItem> itemsToCopy);\n    parameters:\n    - id: itemsToCopy\n      type: System.Collections.Generic.List{System.Activities.Presentation.Model.ModelItem}\n      description: Parameter description to be filled\n    return:\n      type: System.Object\n      description: Parameter description to be filled\n  platform:\n  - net-11\n  - net-20\n  - netcore-10\n- uid: System.Activities.Presentation.ICompositeView.OnItemsCut(System.Collections.Generic.List{System.Activities.Presentation.Model.ModelItem})\n  id: OnItemsCut(System.Collections.Generic.List{System.Activities.Presentation.Model.ModelItem})\n  parent: System.Activities.Presentation.ICompositeView\n  langs:\n  - csharp\n  name: OnItemsCut(List<ModelItem>)\n  nameWithType: ICompositeView.OnItemsCut(List<ModelItem>)\n  fullName: System.Activities.Presentation.ICompositeView.OnItemsCut(List<ModelItem>)\n  type: Method\n  assemblies:\n  - System.Activities.Presentation\n  namespace: System.Activities.Presentation\n  syntax:\n    content: public object OnItemsCut (System.Collections.Generic.List<System.Activities.Presentation.Model.ModelItem> itemsToCut);\n    parameters:\n    - id: itemsToCut\n      type: System.Collections.Generic.List{System.Activities.Presentation.Model.ModelItem}\n      description: Parameter description to be filled\n    return:\n      type: System.Object\n      description: Parameter description to be filled\n  platform:\n  - net-11\n  - net-20\n  - netcore-10\n- uid: System.Activities.Presentation.ICompositeView.OnItemsDelete(System.Collections.Generic.List{System.Activities.Presentation.Model.ModelItem})\n  id: OnItemsDelete(System.Collections.Generic.List{System.Activities.Presentation.Model.ModelItem})\n  parent: System.Activities.Presentation.ICompositeView\n  langs:\n  - csharp\n  name: OnItemsDelete(List<ModelItem>)\n  nameWithType: ICompositeView.OnItemsDelete(List<ModelItem>)\n  fullName: System.Activities.Presentation.ICompositeView.OnItemsDelete(List<ModelItem>)\n  type: Method\n  assemblies:\n  - System.Activities.Presentation\n  namespace: System.Activities.Presentation\n  syntax:\n    content: public void OnItemsDelete (System.Collections.Generic.List<System.Activities.Presentation.Model.ModelItem> itemsToDelete);\n    parameters:\n    - id: itemsToDelete\n      type: System.Collections.Generic.List{System.Activities.Presentation.Model.ModelItem}\n      description: Parameter description to be filled\n  platform:\n  - net-11\n  - net-20\n  - netcore-10\n- uid: System.Activities.Presentation.ICompositeView.OnItemsPasted(System.Collections.Generic.List{System.Object},System.Collections.Generic.List{System.Object},System.Windows.Point,System.Activities.Presentation.WorkflowViewElement)\n  id: OnItemsPasted(System.Collections.Generic.List{System.Object},System.Collections.Generic.List{System.Object},System.Windows.Point,System.Activities.Presentation.WorkflowViewElement)\n  parent: System.Activities.Presentation.ICompositeView\n  langs:\n  - csharp\n  name: OnItemsPasted(List<Object>,List<Object>,Point,WorkflowViewElement)\n  nameWithType: ICompositeView.OnItemsPasted(List<Object>,List<Object>,Point,WorkflowViewElement)\n  fullName: System.Activities.Presentation.ICompositeView.OnItemsPasted(List<Object>,List<Object>,Point,WorkflowViewElement)\n  type: Method\n  assemblies:\n  - System.Activities.Presentation\n  namespace: System.Activities.Presentation\n  syntax:\n    content: public void OnItemsPasted (System.Collections.Generic.List<object> itemsToPaste, System.Collections.Generic.List<object> metadata, System.Windows.Point pastePoint, System.Activities.Presentation.WorkflowViewElement pastePointReference);\n    parameters:\n    - id: itemsToPaste\n      type: System.Collections.Generic.List{System.Object}\n      description: Parameter description to be filled\n    - id: metadata\n      type: System.Collections.Generic.List{System.Object}\n      description: Parameter description to be filled\n    - id: pastePoint\n      type: System.Windows.Point\n      description: Parameter description to be filled\n    - id: pastePointReference\n      type: System.Activities.Presentation.WorkflowViewElement\n      description: Parameter description to be filled\n  platform:\n  - net-11\n  - net-20\n  - netcore-10\nreferences:\n- uid: System.Activities.Presentation.ICompositeView.CanPasteItems(System.Collections.Generic.List{System.Object})\n  parent: System.Activities.Presentation.ICompositeView\n  isExternal: false\n  name: CanPasteItems(List<Object>)\n  nameWithType: ICompositeView.CanPasteItems(List<Object>)\n  fullName: System.Activities.Presentation.ICompositeView.CanPasteItems(List<Object>)\n- uid: System.Boolean\n  parent: System\n  isExternal: false\n  name: Boolean\n  nameWithType: Boolean\n  fullName: System.Boolean\n- uid: System.Collections.Generic.List{System.Object}\n  parent: System.Collections.Generic\n  isExternal: false\n  name: List<Object>\n  nameWithType: List<Object>\n  fullName: System.Collections.Generic.List<System.Object>\n- uid: System.Activities.Presentation.ICompositeView.DroppingTypeResolvingOptions\n  parent: System.Activities.Presentation.ICompositeView\n  isExternal: false\n  name: DroppingTypeResolvingOptions\n  nameWithType: ICompositeView.DroppingTypeResolvingOptions\n  fullName: System.Activities.Presentation.ICompositeView.DroppingTypeResolvingOptions\n- uid: System.Activities.Presentation.View.TypeResolvingOptions\n  parent: System.Activities.Presentation.View\n  isExternal: false\n  name: TypeResolvingOptions\n  nameWithType: TypeResolvingOptions\n  fullName: System.Activities.Presentation.View.TypeResolvingOptions\n- uid: System.Activities.Presentation.ICompositeView.IsDefaultContainer\n  parent: System.Activities.Presentation.ICompositeView\n  isExternal: false\n  name: IsDefaultContainer\n  nameWithType: ICompositeView.IsDefaultContainer\n  fullName: System.Activities.Presentation.ICompositeView.IsDefaultContainer\n- uid: System.Boolean\n  parent: System\n  isExternal: false\n  name: Boolean\n  nameWithType: Boolean\n  fullName: System.Boolean\n- uid: System.Activities.Presentation.ICompositeView.OnItemMoved(System.Activities.Presentation.Model.ModelItem)\n  parent: System.Activities.Presentation.ICompositeView\n  isExternal: false\n  name: OnItemMoved(ModelItem)\n  nameWithType: ICompositeView.OnItemMoved(ModelItem)\n  fullName: System.Activities.Presentation.ICompositeView.OnItemMoved(ModelItem)\n- uid: System.Activities.Presentation.Model.ModelItem\n  parent: System.Activities.Presentation.Model\n  isExternal: false\n  name: ModelItem\n  nameWithType: ModelItem\n  fullName: System.Activities.Presentation.Model.ModelItem\n- uid: System.Activities.Presentation.ICompositeView.OnItemsCopied(System.Collections.Generic.List{System.Activities.Presentation.Model.ModelItem})\n  parent: System.Activities.Presentation.ICompositeView\n  isExternal: false\n  name: OnItemsCopied(List<ModelItem>)\n  nameWithType: ICompositeView.OnItemsCopied(List<ModelItem>)\n  fullName: System.Activities.Presentation.ICompositeView.OnItemsCopied(List<ModelItem>)\n- uid: System.Object\n  parent: System\n  isExternal: false\n  name: Object\n  nameWithType: Object\n  fullName: System.Object\n- uid: System.Collections.Generic.List{System.Activities.Presentation.Model.ModelItem}\n  parent: System.Collections.Generic\n  isExternal: false\n  name: List<ModelItem>\n  nameWithType: List<ModelItem>\n  fullName: System.Collections.Generic.List<System.Activities.Presentation.Model.ModelItem>\n- uid: System.Activities.Presentation.ICompositeView.OnItemsCut(System.Collections.Generic.List{System.Activities.Presentation.Model.ModelItem})\n  parent: System.Activities.Presentation.ICompositeView\n  isExternal: false\n  name: OnItemsCut(List<ModelItem>)\n  nameWithType: ICompositeView.OnItemsCut(List<ModelItem>)\n  fullName: System.Activities.Presentation.ICompositeView.OnItemsCut(List<ModelItem>)\n- uid: System.Object\n  parent: System\n  isExternal: false\n  name: Object\n  nameWithType: Object\n  fullName: System.Object\n- uid: System.Collections.Generic.List{System.Activities.Presentation.Model.ModelItem}\n  parent: System.Collections.Generic\n  isExternal: false\n  name: List<ModelItem>\n  nameWithType: List<ModelItem>\n  fullName: System.Collections.Generic.List<System.Activities.Presentation.Model.ModelItem>\n- uid: System.Activities.Presentation.ICompositeView.OnItemsDelete(System.Collections.Generic.List{System.Activities.Presentation.Model.ModelItem})\n  parent: System.Activities.Presentation.ICompositeView\n  isExternal: false\n  name: OnItemsDelete(List<ModelItem>)\n  nameWithType: ICompositeView.OnItemsDelete(List<ModelItem>)\n  fullName: System.Activities.Presentation.ICompositeView.OnItemsDelete(List<ModelItem>)\n- uid: System.Collections.Generic.List{System.Activities.Presentation.Model.ModelItem}\n  parent: System.Collections.Generic\n  isExternal: false\n  name: List<ModelItem>\n  nameWithType: List<ModelItem>\n  fullName: System.Collections.Generic.List<System.Activities.Presentation.Model.ModelItem>\n- uid: System.Activities.Presentation.ICompositeView.OnItemsPasted(System.Collections.Generic.List{System.Object},System.Collections.Generic.List{System.Object},System.Windows.Point,System.Activities.Presentation.WorkflowViewElement)\n  parent: System.Activities.Presentation.ICompositeView\n  isExternal: false\n  name: OnItemsPasted(List<Object>,List<Object>,Point,WorkflowViewElement)\n  nameWithType: ICompositeView.OnItemsPasted(List<Object>,List<Object>,Point,WorkflowViewElement)\n  fullName: System.Activities.Presentation.ICompositeView.OnItemsPasted(List<Object>,List<Object>,Point,WorkflowViewElement)\n- uid: System.Collections.Generic.List{System.Object}\n  parent: System.Collections.Generic\n  isExternal: false\n  name: List<Object>\n  nameWithType: List<Object>\n  fullName: System.Collections.Generic.List<System.Object>\n- uid: System.Collections.Generic.List{System.Object}\n  parent: System.Collections.Generic\n  isExternal: false\n  name: List<Object>\n  nameWithType: List<Object>\n  fullName: System.Collections.Generic.List<System.Object>\n- uid: System.Windows.Point\n  parent: System.Windows\n  isExternal: true\n  name: Point\n  nameWithType: Point\n  fullName: System.Windows.Point\n- uid: System.Activities.Presentation.WorkflowViewElement\n  parent: System.Activities.Presentation\n  isExternal: false\n  name: WorkflowViewElement\n  nameWithType: WorkflowViewElement\n  fullName: System.Activities.Presentation.WorkflowViewElement\n"}