{"nodes":[{"pos":[198,212],"content":"IEnumerator<ph id=\"ph1\">&lt;T&gt;</ph>","needQuote":true,"needEscape":true,"source":"IEnumerator<T>"},{"pos":[474,508],"content":"Parameter description to be filled","needQuote":true,"needEscape":true,"nodes":[{"content":"Parameter description to be filled","pos":[0,34]}]},{"pos":[779,786],"content":"Current","needQuote":true,"needEscape":true,"nodes":[{"content":"Current","pos":[0,7]}]},{"pos":[1066,1100],"content":"Parameter description to be filled","needQuote":true,"needEscape":true,"nodes":[{"content":"Parameter description to be filled","pos":[0,34]}]},{"pos":[1297,1304],"content":"Current","needQuote":true,"needEscape":true,"nodes":[{"content":"Current","pos":[0,7]}]},{"pos":[1455,1456],"content":"T","needQuote":true,"needEscape":true,"nodes":[{"content":"T","pos":[0,1]}]}],"content":"### YamlMime:ManagedReference\nitems:\n- uid: System.Collections.Generic.IEnumerator`1\n  id: IEnumerator`1\n  children:\n  - System.Collections.Generic.IEnumerator`1.Current\n  langs:\n  - csharp\n  name: IEnumerator<T>\n  nameWithType: IEnumerator<T>\n  fullName: System.Collections.Generic.IEnumerator<T>\n  type: Interface\n  syntax:\n    content: 'public interface IEnumerator<out T> : IDisposable, System.Collections.IEnumerator'\n    typeParameters:\n    - id: T\n      description: Parameter description to be filled\n  implements:\n  - System.Collections.IEnumerator\n  - System.IDisposable\n  platform:\n  - net-11\n  - net-20\n  - netcore-10\n- uid: System.Collections.Generic.IEnumerator`1.Current\n  id: Current\n  parent: System.Collections.Generic.IEnumerator`1\n  langs:\n  - csharp\n  name: Current\n  nameWithType: IEnumerator<T>.Current\n  fullName: System.Collections.Generic.IEnumerator<T>.Current\n  type: Property\n  assemblies:\n  - mscorlib\n  namespace: System.Collections.Generic\n  syntax:\n    content: public T Current { get; }\n    return:\n      type: T\n      description: Parameter description to be filled\n  platform:\n  - net-11\n  - net-20\n  - netcore-10\nreferences:\n- uid: System.Collections.Generic.IEnumerator`1.Current\n  parent: System.Collections.Generic.IEnumerator`1\n  isExternal: false\n  name: Current\n  nameWithType: IEnumerator<T>.Current\n  fullName: System.Collections.Generic.IEnumerator<T>.Current\n- uid: T\n  parent: ''\n  isExternal: true\n  name: T\n  nameWithType: T\n  fullName: T\n"}